quantbt/__init__.py
quantbt/analysis/__init__.py
quantbt/analysis/monthly.py
quantbt/core/PNL.py
quantbt/core/__init__.py
quantbt/core/backtester.old.py
quantbt/core/backtester.py
quantbt/core/base.py
quantbt/core/calculate_commission.py
quantbt/core/calculate_entry_price.py
quantbt/core/calculate_exit_price.py
quantbt/core/data_module.py
quantbt/core/enums.py
quantbt/core/from_signals.py
quantbt/core/from_trades.py
quantbt/core/helpers.py
quantbt/core/place_orders_on_ohlc.py
quantbt/core/specs_nb.py
quantbt/core/test.py
quantbt/core/trade_add_trade_to_active_trades.py
quantbt/core/trade_close_trade.py
quantbt/core/trade_create_new_trade.py
quantbt/core/trade_module.py
quantbt/core/trade_remove_from_active_trades.py
quantbt/core/trade_should_trade_close.py
quantbt/data/__init__.py
quantbt/data/create_binance_dataframe.py
quantbt/data/fetch_binance_data.py
quantbt/data/get_local_data.py
quantbt/data/random_data.py
quantbt/data/resample.py
quantbt/data/trading_strategy.py
quantbt/helpers/H_ticks_to_ranges.py
quantbt/helpers/S_calculate_metrics.py
quantbt/helpers/S_print_orders.py
quantbt/helpers/S_print_trades.py
quantbt/helpers/__init__.py
quantbt/helpers/analyze_trade_duration.py
quantbt/helpers/backtest.py
quantbt/helpers/calculate_average_freq.py
quantbt/helpers/calculate_pf_stats.py
quantbt/helpers/calculate_risk_free.py
quantbt/helpers/get_average_trade_duration.py
quantbt/helpers/get_realized_pf_value.py
quantbt/helpers/plot_barchart.py
quantbt/helpers/plot_lines.py
quantbt/helpers/plot_returns_heatmap.py
quantbt/helpers/save_to_csv.py
quantbt/indicators/ATR.py
quantbt/indicators/EMA.py
quantbt/indicators/HMA.py
quantbt/indicators/I_HA.py
quantbt/indicators/I_donchian.py
quantbt/indicators/SMA.py
quantbt/indicators/__init__.py
quantbt/indicators/cross_above.py
quantbt/indicators/cross_below.py
quantbt/indicators/supertrend.py
quantbt/lib/__init__.py
quantbt/lib/calculate_stats.py
quantbt/lib/convert_signal_to_markers.py
quantbt/lib/data_to_csv.py
quantbt-0.9.4.dist-info/METADATA
quantbt-0.9.4.dist-info/WHEEL
quantbt-0.9.4.dist-info/RECORD
